{
  "ids_info": {
    "name": "iron_core",
    "description": "Iron core description",
    "version": "4.0.1.dev164",
    "max_depth": 6,
    "leaf_count": 164,
    "physics_domain": "coils",
    "documentation_coverage": 1.0,
    "related_ids": [],
    "common_use_cases": []
  },
  "coordinate_systems": {},
  "paths": {
    "iron_core/segment": {
      "path": "iron_core/segment",
      "documentation": "The iron core is describred as a set of segments",
      "units": "",
      "coordinates": [
        "1...N"
      ],
      "lifecycle": "active",
      "data_type": "struct_array",
      "introduced_after": null,
      "physics_context": null,
      "related_paths": [
        "segment/name",
        "segment/description",
        "segment/b_field"
      ],
      "usage_examples": [],
      "validation_rules": {
        "min_value": null,
        "max_value": null,
        "units_required": false,
        "coordinate_check": null
      },
      "relationships": {
        "coordinates": [],
        "physics_related": [],
        "cross_ids": [],
        "validation": [],
        "hierarchical": [
          "segment/name",
          "segment/description",
          "segment/b_field"
        ],
        "units_compatible": [],
        "semantic_similarity": [],
        "documentation_refs": []
      },
      "coordinate1": null,
      "coordinate2": null,
      "timebase": null,
      "type": null,
      "structure_reference": "iron_core_segment"
    },
    "iron_core/segment/name": {
      "path": "iron_core/segment/name",
      "documentation": "Short string identifier (unique for a given device)",
      "units": "",
      "coordinates": [],
      "lifecycle": "active",
      "data_type": "STR_0D",
      "introduced_after": null,
      "physics_context": null,
      "related_paths": [
        "segment/description",
        "segment/b_field",
        "segment/permeability_relative",
        "segment"
      ],
      "usage_examples": [],
      "validation_rules": {
        "min_value": null,
        "max_value": null,
        "units_required": false,
        "coordinate_check": null
      },
      "relationships": {
        "coordinates": [],
        "physics_related": [],
        "cross_ids": [],
        "validation": [],
        "hierarchical": [
          "segment",
          "segment/description",
          "segment/b_field",
          "segment/permeability_relative"
        ],
        "units_compatible": [],
        "semantic_similarity": [],
        "documentation_refs": []
      },
      "coordinate1": null,
      "coordinate2": null,
      "timebase": null,
      "type": null
    },
    "iron_core/segment/description": {
      "path": "iron_core/segment/description",
      "documentation": "Description, e.g. “channel viewing the upper divertor”",
      "units": "",
      "coordinates": [],
      "lifecycle": "active",
      "data_type": "STR_0D",
      "introduced_after": null,
      "physics_context": null,
      "related_paths": [
        "segment/name",
        "segment/b_field",
        "segment/permeability_relative",
        "segment",
        "segment/geometry/oblique/z"
      ],
      "usage_examples": [],
      "validation_rules": {
        "min_value": null,
        "max_value": null,
        "units_required": false,
        "coordinate_check": null
      },
      "relationships": {
        "coordinates": [],
        "physics_related": [
          "segment/geometry/oblique/z"
        ],
        "cross_ids": [],
        "validation": [],
        "hierarchical": [
          "segment",
          "segment/name",
          "segment/b_field",
          "segment/permeability_relative"
        ],
        "units_compatible": [],
        "semantic_similarity": [],
        "documentation_refs": []
      },
      "coordinate1": null,
      "coordinate2": null,
      "timebase": null,
      "type": null
    },
    "iron_core/segment/b_field": {
      "path": "iron_core/segment/b_field",
      "documentation": "Array of magnetic field values, for each of which the relative permeability is given",
      "units": "T",
      "coordinates": [
        "1...N"
      ],
      "lifecycle": "active",
      "data_type": "FLT_1D",
      "introduced_after": null,
      "physics_context": null,
      "related_paths": [
        "segment/name",
        "segment/description",
        "segment/permeability_relative",
        "segment/magnetization_r",
        "segment"
      ],
      "usage_examples": [],
      "validation_rules": {
        "min_value": null,
        "max_value": null,
        "units_required": true,
        "coordinate_check": null
      },
      "relationships": {
        "coordinates": [],
        "physics_related": [
          "segment/magnetization_r"
        ],
        "cross_ids": [],
        "validation": [],
        "hierarchical": [
          "segment",
          "segment/name",
          "segment/description",
          "segment/permeability_relative"
        ],
        "units_compatible": [],
        "semantic_similarity": [],
        "documentation_refs": []
      },
      "coordinate1": null,
      "coordinate2": null,
      "timebase": null,
      "type": null
    },
    "iron_core/segment/permeability_relative": {
      "path": "iron_core/segment/permeability_relative",
      "documentation": "Relative permeability of the iron segment",
      "units": "1",
      "coordinates": [
        "segment(i1)/b_field"
      ],
      "lifecycle": "active",
      "data_type": "FLT_1D",
      "introduced_after": null,
      "physics_context": null,
      "related_paths": [
        "segment/name",
        "segment/description",
        "segment/b_field",
        "segment",
        "segment/geometry/oblique/z"
      ],
      "usage_examples": [],
      "validation_rules": {
        "min_value": null,
        "max_value": null,
        "units_required": false,
        "coordinate_check": null
      },
      "relationships": {
        "coordinates": [],
        "physics_related": [
          "segment/geometry/oblique/z"
        ],
        "cross_ids": [],
        "validation": [],
        "hierarchical": [
          "segment",
          "segment/name",
          "segment/description",
          "segment/b_field"
        ],
        "units_compatible": [],
        "semantic_similarity": [],
        "documentation_refs": []
      },
      "coordinate1": null,
      "coordinate2": null,
      "timebase": null,
      "type": null
    },
    "iron_core/segment/geometry": {
      "path": "iron_core/segment/geometry",
      "documentation": "Cross-sectional shape of the segment",
      "units": "",
      "coordinates": [],
      "lifecycle": "active",
      "data_type": "structure",
      "introduced_after": null,
      "physics_context": null,
      "related_paths": [
        "segment/name",
        "segment/description",
        "segment/b_field",
        "segment",
        "segment/geometry/geometry_type",
        "segment/geometry/outline",
        "segment/geometry/rectangle",
        "segment/geometry/oblique",
        "segment/geometry/arcs_of_circle",
        "segment/geometry/oblique/z"
      ],
      "usage_examples": [],
      "validation_rules": {
        "min_value": null,
        "max_value": null,
        "units_required": false,
        "coordinate_check": null
      },
      "relationships": {
        "coordinates": [],
        "physics_related": [
          "segment/geometry/oblique/z"
        ],
        "cross_ids": [],
        "validation": [],
        "hierarchical": [
          "segment",
          "segment/name",
          "segment/description",
          "segment/b_field",
          "segment/geometry/geometry_type",
          "segment/geometry/outline",
          "segment/geometry/rectangle",
          "segment/geometry/oblique",
          "segment/geometry/arcs_of_circle"
        ],
        "units_compatible": [],
        "semantic_similarity": [],
        "documentation_refs": []
      },
      "coordinate1": null,
      "coordinate2": null,
      "timebase": null,
      "type": null,
      "structure_reference": "outline_2d_geometry_static"
    },
    "iron_core/segment/geometry/geometry_type": {
      "path": "iron_core/segment/geometry/geometry_type",
      "documentation": "Type used to describe the element shape (1:'outline', 2:'rectangle', 3:'oblique', 4:'arcs of circle, 5: 'annulus', 6 : 'thick line')",
      "units": "",
      "coordinates": [],
      "lifecycle": "active",
      "data_type": "INT_0D",
      "introduced_after": null,
      "physics_context": null,
      "related_paths": [
        "segment/geometry/outline",
        "segment/geometry/rectangle",
        "segment/geometry/oblique",
        "segment/geometry/arcs_of_circle",
        "segment/geometry/annulus",
        "segment/geometry",
        "segment/geometry/oblique/z"
      ],
      "usage_examples": [],
      "validation_rules": {
        "min_value": null,
        "max_value": null,
        "units_required": false,
        "coordinate_check": null
      },
      "relationships": {
        "coordinates": [],
        "physics_related": [
          "segment/geometry/oblique/z"
        ],
        "cross_ids": [],
        "validation": [],
        "hierarchical": [
          "segment/geometry",
          "segment/geometry/outline",
          "segment/geometry/rectangle",
          "segment/geometry/oblique",
          "segment/geometry/arcs_of_circle",
          "segment/geometry/annulus"
        ],
        "units_compatible": [],
        "semantic_similarity": [],
        "documentation_refs": []
      },
      "coordinate1": null,
      "coordinate2": null,
      "timebase": null,
      "type": null
    },
    "iron_core/segment/geometry/outline": {
      "path": "iron_core/segment/geometry/outline",
      "documentation": "Irregular outline of the element. Repeat the first point since this is a closed contour",
      "units": "",
      "coordinates": [],
      "lifecycle": "active",
      "data_type": "structure",
      "introduced_after": null,
      "physics_context": null,
      "related_paths": [
        "segment/geometry/geometry_type",
        "segment/geometry/rectangle",
        "segment/geometry/oblique",
        "segment/geometry/arcs_of_circle",
        "segment/geometry/annulus",
        "segment/geometry",
        "segment/geometry/outline/r",
        "segment/geometry/outline/z",
        "segment/geometry/oblique/z"
      ],
      "usage_examples": [],
      "validation_rules": {
        "min_value": null,
        "max_value": null,
        "units_required": false,
        "coordinate_check": null
      },
      "relationships": {
        "coordinates": [],
        "physics_related": [
          "segment/geometry/oblique/z"
        ],
        "cross_ids": [],
        "validation": [],
        "hierarchical": [
          "segment/geometry",
          "segment/geometry/geometry_type",
          "segment/geometry/rectangle",
          "segment/geometry/oblique",
          "segment/geometry/arcs_of_circle",
          "segment/geometry/annulus",
          "segment/geometry/outline/r",
          "segment/geometry/outline/z"
        ],
        "units_compatible": [],
        "semantic_similarity": [],
        "documentation_refs": []
      },
      "coordinate1": null,
      "coordinate2": null,
      "timebase": null,
      "type": null,
      "structure_reference": "rz1d_static"
    },
    "iron_core/segment/geometry/outline/r": {
      "path": "iron_core/segment/geometry/outline/r",
      "documentation": "Major radius",
      "units": "m",
      "coordinates": [
        "1...N"
      ],
      "lifecycle": "active",
      "data_type": "FLT_1D",
      "introduced_after": null,
      "physics_context": null,
      "related_paths": [
        "segment/geometry/outline/z",
        "segment/geometry/oblique/z",
        "segment/geometry/outline"
      ],
      "usage_examples": [],
      "validation_rules": {
        "min_value": null,
        "max_value": null,
        "units_required": true,
        "coordinate_check": null
      },
      "relationships": {
        "coordinates": [],
        "physics_related": [
          "segment/geometry/oblique/z",
          "segment/geometry/outline/z"
        ],
        "cross_ids": [],
        "validation": [],
        "hierarchical": [
          "segment/geometry/outline",
          "segment/geometry/outline/z"
        ],
        "units_compatible": [],
        "semantic_similarity": [],
        "documentation_refs": []
      },
      "coordinate1": null,
      "coordinate2": null,
      "timebase": null,
      "type": null
    },
    "iron_core/segment/geometry/outline/z": {
      "path": "iron_core/segment/geometry/outline/z",
      "documentation": "Height",
      "units": "m",
      "coordinates": [
        "segment(i1)/geometry/outline/r"
      ],
      "lifecycle": "active",
      "data_type": "FLT_1D",
      "introduced_after": null,
      "physics_context": null,
      "related_paths": [
        "segment/geometry/outline/r",
        "segment/geometry/oblique/z",
        "segment/geometry/outline"
      ],
      "usage_examples": [],
      "validation_rules": {
        "min_value": null,
        "max_value": null,
        "units_required": true,
        "coordinate_check": null
      },
      "relationships": {
        "coordinates": [],
        "physics_related": [
          "segment/geometry/oblique/z",
          "segment/geometry/outline/r"
        ],
        "cross_ids": [],
        "validation": [],
        "hierarchical": [
          "segment/geometry/outline",
          "segment/geometry/outline/r"
        ],
        "units_compatible": [],
        "semantic_similarity": [],
        "documentation_refs": []
      },
      "coordinate1": null,
      "coordinate2": null,
      "timebase": null,
      "type": null
    },
    "iron_core/segment/geometry/rectangle": {
      "path": "iron_core/segment/geometry/rectangle",
      "documentation": "Rectangular description of the element",
      "units": "",
      "coordinates": [],
      "lifecycle": "active",
      "data_type": "structure",
      "introduced_after": null,
      "physics_context": null,
      "related_paths": [
        "segment/geometry/geometry_type",
        "segment/geometry/outline",
        "segment/geometry/oblique",
        "segment/geometry/arcs_of_circle",
        "segment/geometry/annulus",
        "segment/geometry",
        "segment/geometry/rectangle/r",
        "segment/geometry/rectangle/z",
        "segment/geometry/oblique/z"
      ],
      "usage_examples": [],
      "validation_rules": {
        "min_value": null,
        "max_value": null,
        "units_required": false,
        "coordinate_check": null
      },
      "relationships": {
        "coordinates": [],
        "physics_related": [
          "segment/geometry/oblique/z"
        ],
        "cross_ids": [],
        "validation": [],
        "hierarchical": [
          "segment/geometry",
          "segment/geometry/geometry_type",
          "segment/geometry/outline",
          "segment/geometry/oblique",
          "segment/geometry/arcs_of_circle",
          "segment/geometry/annulus",
          "segment/geometry/rectangle/r",
          "segment/geometry/rectangle/z"
        ],
        "units_compatible": [],
        "semantic_similarity": [],
        "documentation_refs": []
      },
      "coordinate1": null,
      "coordinate2": null,
      "timebase": null,
      "type": null,
      "structure_reference": "rectangle_static"
    },
    "iron_core/segment/geometry/rectangle/r": {
      "path": "iron_core/segment/geometry/rectangle/r",
      "documentation": "Geometric centre R",
      "units": "m",
      "coordinates": [],
      "lifecycle": "active",
      "data_type": "FLT_0D",
      "introduced_after": null,
      "physics_context": null,
      "related_paths": [
        "segment/geometry/rectangle/z",
        "segment/geometry/oblique/z",
        "segment/geometry/outline/r",
        "segment/geometry/rectangle"
      ],
      "usage_examples": [],
      "validation_rules": {
        "min_value": null,
        "max_value": null,
        "units_required": true,
        "coordinate_check": null
      },
      "relationships": {
        "coordinates": [],
        "physics_related": [
          "segment/geometry/oblique/z",
          "segment/geometry/outline/r"
        ],
        "cross_ids": [],
        "validation": [],
        "hierarchical": [
          "segment/geometry/rectangle",
          "segment/geometry/rectangle/z"
        ],
        "units_compatible": [],
        "semantic_similarity": [],
        "documentation_refs": []
      },
      "coordinate1": null,
      "coordinate2": null,
      "timebase": null,
      "type": null
    },
    "iron_core/segment/geometry/rectangle/z": {
      "path": "iron_core/segment/geometry/rectangle/z",
      "documentation": "Geometric centre Z",
      "units": "m",
      "coordinates": [],
      "lifecycle": "active",
      "data_type": "FLT_0D",
      "introduced_after": null,
      "physics_context": null,
      "related_paths": [
        "segment/geometry/rectangle/r",
        "segment/geometry/oblique/z",
        "segment/geometry/outline/r",
        "segment/geometry/rectangle"
      ],
      "usage_examples": [],
      "validation_rules": {
        "min_value": null,
        "max_value": null,
        "units_required": true,
        "coordinate_check": null
      },
      "relationships": {
        "coordinates": [],
        "physics_related": [
          "segment/geometry/oblique/z",
          "segment/geometry/outline/r"
        ],
        "cross_ids": [],
        "validation": [],
        "hierarchical": [
          "segment/geometry/rectangle",
          "segment/geometry/rectangle/r"
        ],
        "units_compatible": [],
        "semantic_similarity": [],
        "documentation_refs": []
      },
      "coordinate1": null,
      "coordinate2": null,
      "timebase": null,
      "type": null
    },
    "iron_core/segment/geometry/rectangle/width": {
      "path": "iron_core/segment/geometry/rectangle/width",
      "documentation": "Horizontal full width",
      "units": "m",
      "coordinates": [],
      "lifecycle": "active",
      "data_type": "FLT_0D",
      "introduced_after": null,
      "physics_context": null,
      "related_paths": [
        "segment/geometry/rectangle/r",
        "segment/geometry/rectangle/z",
        "segment/geometry/oblique/z",
        "segment/geometry/outline/r",
        "segment/geometry/rectangle"
      ],
      "usage_examples": [],
      "validation_rules": {
        "min_value": null,
        "max_value": null,
        "units_required": true,
        "coordinate_check": null
      },
      "relationships": {
        "coordinates": [],
        "physics_related": [
          "segment/geometry/oblique/z",
          "segment/geometry/outline/r"
        ],
        "cross_ids": [],
        "validation": [],
        "hierarchical": [
          "segment/geometry/rectangle",
          "segment/geometry/rectangle/r",
          "segment/geometry/rectangle/z"
        ],
        "units_compatible": [],
        "semantic_similarity": [],
        "documentation_refs": []
      },
      "coordinate1": null,
      "coordinate2": null,
      "timebase": null,
      "type": null
    },
    "iron_core/segment/geometry/rectangle/height": {
      "path": "iron_core/segment/geometry/rectangle/height",
      "documentation": "Vertical full height",
      "units": "m",
      "coordinates": [],
      "lifecycle": "active",
      "data_type": "FLT_0D",
      "introduced_after": null,
      "physics_context": null,
      "related_paths": [
        "segment/geometry/rectangle/r",
        "segment/geometry/rectangle/z",
        "segment/geometry/oblique/z",
        "segment/geometry/outline/r",
        "segment/geometry/rectangle"
      ],
      "usage_examples": [],
      "validation_rules": {
        "min_value": null,
        "max_value": null,
        "units_required": true,
        "coordinate_check": null
      },
      "relationships": {
        "coordinates": [],
        "physics_related": [
          "segment/geometry/oblique/z",
          "segment/geometry/outline/r"
        ],
        "cross_ids": [],
        "validation": [],
        "hierarchical": [
          "segment/geometry/rectangle",
          "segment/geometry/rectangle/r",
          "segment/geometry/rectangle/z"
        ],
        "units_compatible": [],
        "semantic_similarity": [],
        "documentation_refs": []
      },
      "coordinate1": null,
      "coordinate2": null,
      "timebase": null,
      "type": null
    },
    "iron_core/segment/geometry/oblique": {
      "path": "iron_core/segment/geometry/oblique",
      "documentation": "Parallelogram description of the element",
      "units": "",
      "coordinates": [],
      "lifecycle": "active",
      "data_type": "structure",
      "introduced_after": null,
      "physics_context": null,
      "related_paths": [
        "segment/geometry/geometry_type",
        "segment/geometry/outline",
        "segment/geometry/rectangle",
        "segment/geometry/arcs_of_circle",
        "segment/geometry/annulus",
        "segment/geometry",
        "segment/geometry/oblique/r",
        "segment/geometry/oblique/z"
      ],
      "usage_examples": [],
      "validation_rules": {
        "min_value": null,
        "max_value": null,
        "units_required": false,
        "coordinate_check": null
      },
      "relationships": {
        "coordinates": [],
        "physics_related": [
          "segment/geometry/oblique/z"
        ],
        "cross_ids": [],
        "validation": [],
        "hierarchical": [
          "segment/geometry",
          "segment/geometry/geometry_type",
          "segment/geometry/outline",
          "segment/geometry/rectangle",
          "segment/geometry/arcs_of_circle",
          "segment/geometry/annulus",
          "segment/geometry/oblique/r",
          "segment/geometry/oblique/z"
        ],
        "units_compatible": [],
        "semantic_similarity": [],
        "documentation_refs": []
      },
      "coordinate1": null,
      "coordinate2": null,
      "timebase": null,
      "type": null,
      "structure_reference": "oblique_static"
    },
    "iron_core/segment/geometry/oblique/r": {
      "path": "iron_core/segment/geometry/oblique/r",
      "documentation": "Major radius of the reference point (from which the alpha and beta angles are defined, marked by a + on the diagram)",
      "units": "m",
      "coordinates": [],
      "lifecycle": "active",
      "data_type": "FLT_0D",
      "introduced_after": null,
      "physics_context": null,
      "related_paths": [
        "segment/geometry/oblique/z",
        "segment/geometry/outline/r",
        "segment/geometry/oblique"
      ],
      "usage_examples": [],
      "validation_rules": {
        "min_value": null,
        "max_value": null,
        "units_required": true,
        "coordinate_check": null
      },
      "relationships": {
        "coordinates": [],
        "physics_related": [
          "segment/geometry/oblique/z",
          "segment/geometry/outline/r"
        ],
        "cross_ids": [],
        "validation": [],
        "hierarchical": [
          "segment/geometry/oblique",
          "segment/geometry/oblique/z"
        ],
        "units_compatible": [],
        "semantic_similarity": [],
        "documentation_refs": []
      },
      "coordinate1": null,
      "coordinate2": null,
      "timebase": null,
      "type": null
    },
    "iron_core/segment/geometry/oblique/z": {
      "path": "iron_core/segment/geometry/oblique/z",
      "documentation": "Height of the reference point (from which the alpha and beta angles are defined, marked by a + on the diagram)",
      "units": "m",
      "coordinates": [],
      "lifecycle": "active",
      "data_type": "FLT_0D",
      "introduced_after": null,
      "physics_context": null,
      "related_paths": [
        "segment/geometry/oblique/r",
        "segment/geometry/outline/r",
        "segment/geometry/oblique"
      ],
      "usage_examples": [],
      "validation_rules": {
        "min_value": null,
        "max_value": null,
        "units_required": true,
        "coordinate_check": null
      },
      "relationships": {
        "coordinates": [],
        "physics_related": [
          "segment/geometry/outline/r"
        ],
        "cross_ids": [],
        "validation": [],
        "hierarchical": [
          "segment/geometry/oblique",
          "segment/geometry/oblique/r"
        ],
        "units_compatible": [],
        "semantic_similarity": [],
        "documentation_refs": []
      },
      "coordinate1": null,
      "coordinate2": null,
      "timebase": null,
      "type": null
    },
    "iron_core/segment/geometry/oblique/length_alpha": {
      "path": "iron_core/segment/geometry/oblique/length_alpha",
      "documentation": "Length of the parallelogram side inclined with angle alpha with respect to the major radius axis",
      "units": "m",
      "coordinates": [],
      "lifecycle": "active",
      "data_type": "FLT_0D",
      "introduced_after": null,
      "physics_context": null,
      "related_paths": [
        "segment/geometry/oblique/r",
        "segment/geometry/oblique/z",
        "segment/geometry/outline/r",
        "segment/geometry/oblique"
      ],
      "usage_examples": [],
      "validation_rules": {
        "min_value": null,
        "max_value": null,
        "units_required": true,
        "coordinate_check": null
      },
      "relationships": {
        "coordinates": [],
        "physics_related": [
          "segment/geometry/oblique/z",
          "segment/geometry/outline/r"
        ],
        "cross_ids": [],
        "validation": [],
        "hierarchical": [
          "segment/geometry/oblique",
          "segment/geometry/oblique/r",
          "segment/geometry/oblique/z"
        ],
        "units_compatible": [],
        "semantic_similarity": [],
        "documentation_refs": []
      },
      "coordinate1": null,
      "coordinate2": null,
      "timebase": null,
      "type": null
    },
    "iron_core/segment/geometry/oblique/length_beta": {
      "path": "iron_core/segment/geometry/oblique/length_beta",
      "documentation": "Length of the parallelogram side inclined with angle beta with respect to the height axis",
      "units": "m",
      "coordinates": [],
      "lifecycle": "active",
      "data_type": "FLT_0D",
      "introduced_after": null,
      "physics_context": null,
      "related_paths": [
        "segment/geometry/oblique/r",
        "segment/geometry/oblique/z",
        "segment/geometry/outline/r",
        "segment/geometry/oblique"
      ],
      "usage_examples": [],
      "validation_rules": {
        "min_value": null,
        "max_value": null,
        "units_required": true,
        "coordinate_check": null
      },
      "relationships": {
        "coordinates": [],
        "physics_related": [
          "segment/geometry/oblique/z",
          "segment/geometry/outline/r"
        ],
        "cross_ids": [],
        "validation": [],
        "hierarchical": [
          "segment/geometry/oblique",
          "segment/geometry/oblique/r",
          "segment/geometry/oblique/z"
        ],
        "units_compatible": [],
        "semantic_similarity": [],
        "documentation_refs": []
      },
      "coordinate1": null,
      "coordinate2": null,
      "timebase": null,
      "type": null
    },
    "iron_core/segment/geometry/oblique/alpha": {
      "path": "iron_core/segment/geometry/oblique/alpha",
      "documentation": "Inclination of first angle measured counter-clockwise from horizontal outwardly directed radial vector (grad R).",
      "units": "rad",
      "coordinates": [],
      "lifecycle": "active",
      "data_type": "FLT_0D",
      "introduced_after": null,
      "physics_context": null,
      "related_paths": [
        "segment/geometry/oblique/r",
        "segment/geometry/oblique/z",
        "segment/geometry/oblique/beta",
        "segment/geometry/oblique"
      ],
      "usage_examples": [],
      "validation_rules": {
        "min_value": null,
        "max_value": null,
        "units_required": true,
        "coordinate_check": null
      },
      "relationships": {
        "coordinates": [],
        "physics_related": [
          "segment/geometry/oblique/z",
          "segment/geometry/oblique/beta"
        ],
        "cross_ids": [],
        "validation": [],
        "hierarchical": [
          "segment/geometry/oblique",
          "segment/geometry/oblique/r",
          "segment/geometry/oblique/z"
        ],
        "units_compatible": [],
        "semantic_similarity": [],
        "documentation_refs": []
      },
      "coordinate1": null,
      "coordinate2": null,
      "timebase": null,
      "type": null
    },
    "iron_core/segment/geometry/oblique/beta": {
      "path": "iron_core/segment/geometry/oblique/beta",
      "documentation": "Inclination of second angle measured counter-clockwise from vertically upwards directed vector (grad Z). If both alpha and beta are zero (rectangle) then the simpler rectangular elements description should be used.",
      "units": "rad",
      "coordinates": [],
      "lifecycle": "active",
      "data_type": "FLT_0D",
      "introduced_after": null,
      "physics_context": null,
      "related_paths": [
        "segment/geometry/oblique/r",
        "segment/geometry/oblique/z",
        "segment/geometry/oblique/alpha",
        "segment/geometry/oblique"
      ],
      "usage_examples": [],
      "validation_rules": {
        "min_value": null,
        "max_value": null,
        "units_required": true,
        "coordinate_check": null
      },
      "relationships": {
        "coordinates": [],
        "physics_related": [
          "segment/geometry/oblique/z",
          "segment/geometry/oblique/alpha"
        ],
        "cross_ids": [],
        "validation": [],
        "hierarchical": [
          "segment/geometry/oblique",
          "segment/geometry/oblique/r",
          "segment/geometry/oblique/z"
        ],
        "units_compatible": [],
        "semantic_similarity": [],
        "documentation_refs": []
      },
      "coordinate1": null,
      "coordinate2": null,
      "timebase": null,
      "type": null
    },
    "iron_core/segment/geometry/arcs_of_circle": {
      "path": "iron_core/segment/geometry/arcs_of_circle",
      "documentation": "Description of the element contour by a set of arcs of circle. For each of these, the position of the start point is given together with the curvature radius. The end point is given by the start point of the next arc of circle.",
      "units": "",
      "coordinates": [],
      "lifecycle": "active",
      "data_type": "structure",
      "introduced_after": null,
      "physics_context": null,
      "related_paths": [
        "segment/geometry/geometry_type",
        "segment/geometry/outline",
        "segment/geometry/rectangle",
        "segment/geometry/oblique",
        "segment/geometry/annulus",
        "segment/geometry",
        "segment/geometry/arcs_of_circle/r",
        "segment/geometry/arcs_of_circle/z",
        "segment/geometry/oblique/z"
      ],
      "usage_examples": [],
      "validation_rules": {
        "min_value": null,
        "max_value": null,
        "units_required": false,
        "coordinate_check": null
      },
      "relationships": {
        "coordinates": [],
        "physics_related": [
          "segment/geometry/oblique/z"
        ],
        "cross_ids": [],
        "validation": [],
        "hierarchical": [
          "segment/geometry",
          "segment/geometry/geometry_type",
          "segment/geometry/outline",
          "segment/geometry/rectangle",
          "segment/geometry/oblique",
          "segment/geometry/annulus",
          "segment/geometry/arcs_of_circle/r",
          "segment/geometry/arcs_of_circle/z"
        ],
        "units_compatible": [],
        "semantic_similarity": [],
        "documentation_refs": []
      },
      "coordinate1": null,
      "coordinate2": null,
      "timebase": null,
      "type": null,
      "structure_reference": "arcs_of_circle_static"
    },
    "iron_core/segment/geometry/arcs_of_circle/r": {
      "path": "iron_core/segment/geometry/arcs_of_circle/r",
      "documentation": "Major radii of the start point of each arc of circle",
      "units": "m",
      "coordinates": [
        "1...N"
      ],
      "lifecycle": "active",
      "data_type": "FLT_1D",
      "introduced_after": null,
      "physics_context": null,
      "related_paths": [
        "segment/geometry/arcs_of_circle/z",
        "segment/geometry/oblique/z",
        "segment/geometry/outline/r",
        "segment/geometry/arcs_of_circle"
      ],
      "usage_examples": [],
      "validation_rules": {
        "min_value": null,
        "max_value": null,
        "units_required": true,
        "coordinate_check": null
      },
      "relationships": {
        "coordinates": [],
        "physics_related": [
          "segment/geometry/oblique/z",
          "segment/geometry/outline/r"
        ],
        "cross_ids": [],
        "validation": [],
        "hierarchical": [
          "segment/geometry/arcs_of_circle",
          "segment/geometry/arcs_of_circle/z"
        ],
        "units_compatible": [],
        "semantic_similarity": [],
        "documentation_refs": []
      },
      "coordinate1": null,
      "coordinate2": null,
      "timebase": null,
      "type": null
    },
    "iron_core/segment/geometry/arcs_of_circle/z": {
      "path": "iron_core/segment/geometry/arcs_of_circle/z",
      "documentation": "Height of the start point of each arc of circle",
      "units": "m",
      "coordinates": [
        "segment(i1)/geometry/arcs_of_circle/r"
      ],
      "lifecycle": "active",
      "data_type": "FLT_1D",
      "introduced_after": null,
      "physics_context": null,
      "related_paths": [
        "segment/geometry/arcs_of_circle/r",
        "segment/geometry/oblique/z",
        "segment/geometry/outline/r",
        "segment/geometry/arcs_of_circle/curvature_radii",
        "segment/geometry/arcs_of_circle"
      ],
      "usage_examples": [],
      "validation_rules": {
        "min_value": null,
        "max_value": null,
        "units_required": true,
        "coordinate_check": null
      },
      "relationships": {
        "coordinates": [
          "segment/geometry/arcs_of_circle/curvature_radii"
        ],
        "physics_related": [
          "segment/geometry/oblique/z",
          "segment/geometry/outline/r"
        ],
        "cross_ids": [],
        "validation": [],
        "hierarchical": [
          "segment/geometry/arcs_of_circle",
          "segment/geometry/arcs_of_circle/r"
        ],
        "units_compatible": [],
        "semantic_similarity": [],
        "documentation_refs": []
      },
      "coordinate1": null,
      "coordinate2": null,
      "timebase": null,
      "type": null
    },
    "iron_core/segment/geometry/arcs_of_circle/curvature_radii": {
      "path": "iron_core/segment/geometry/arcs_of_circle/curvature_radii",
      "documentation": "Curvature radius of each arc of circle",
      "units": "m",
      "coordinates": [
        "segment(i1)/geometry/arcs_of_circle/r"
      ],
      "lifecycle": "active",
      "data_type": "FLT_1D",
      "introduced_after": null,
      "physics_context": null,
      "related_paths": [
        "segment/geometry/arcs_of_circle/r",
        "segment/geometry/arcs_of_circle/z",
        "segment/geometry/oblique/z",
        "segment/geometry/outline/r",
        "segment/geometry/arcs_of_circle"
      ],
      "usage_examples": [],
      "validation_rules": {
        "min_value": null,
        "max_value": null,
        "units_required": true,
        "coordinate_check": null
      },
      "relationships": {
        "coordinates": [
          "segment/geometry/arcs_of_circle/z"
        ],
        "physics_related": [
          "segment/geometry/oblique/z",
          "segment/geometry/outline/r"
        ],
        "cross_ids": [],
        "validation": [],
        "hierarchical": [
          "segment/geometry/arcs_of_circle",
          "segment/geometry/arcs_of_circle/r",
          "segment/geometry/arcs_of_circle/z"
        ],
        "units_compatible": [],
        "semantic_similarity": [],
        "documentation_refs": []
      },
      "coordinate1": null,
      "coordinate2": null,
      "timebase": null,
      "type": null
    },
    "iron_core/segment/geometry/annulus": {
      "path": "iron_core/segment/geometry/annulus",
      "documentation": "The element is an annulus of centre R, Z, with inner radius radius_inner and outer radius radius_outer",
      "units": "",
      "coordinates": [],
      "lifecycle": "active",
      "data_type": "structure",
      "introduced_after": null,
      "physics_context": null,
      "related_paths": [
        "segment/geometry/geometry_type",
        "segment/geometry/outline",
        "segment/geometry/rectangle",
        "segment/geometry/oblique",
        "segment/geometry/arcs_of_circle",
        "segment/geometry",
        "segment/geometry/annulus/r",
        "segment/geometry/annulus/z",
        "segment/geometry/oblique/z"
      ],
      "usage_examples": [],
      "validation_rules": {
        "min_value": null,
        "max_value": null,
        "units_required": false,
        "coordinate_check": null
      },
      "relationships": {
        "coordinates": [],
        "physics_related": [
          "segment/geometry/oblique/z"
        ],
        "cross_ids": [],
        "validation": [],
        "hierarchical": [
          "segment/geometry",
          "segment/geometry/geometry_type",
          "segment/geometry/outline",
          "segment/geometry/rectangle",
          "segment/geometry/oblique",
          "segment/geometry/arcs_of_circle",
          "segment/geometry/annulus/r",
          "segment/geometry/annulus/z"
        ],
        "units_compatible": [],
        "semantic_similarity": [],
        "documentation_refs": []
      },
      "coordinate1": null,
      "coordinate2": null,
      "timebase": null,
      "type": null,
      "structure_reference": "annulus_static"
    },
    "iron_core/segment/geometry/annulus/r": {
      "path": "iron_core/segment/geometry/annulus/r",
      "documentation": "Centre major radius",
      "units": "m",
      "coordinates": [],
      "lifecycle": "active",
      "data_type": "FLT_0D",
      "introduced_after": null,
      "physics_context": null,
      "related_paths": [
        "segment/geometry/annulus/z",
        "segment/geometry/oblique/z",
        "segment/geometry/outline/r",
        "segment/geometry/annulus"
      ],
      "usage_examples": [],
      "validation_rules": {
        "min_value": null,
        "max_value": null,
        "units_required": true,
        "coordinate_check": null
      },
      "relationships": {
        "coordinates": [],
        "physics_related": [
          "segment/geometry/oblique/z",
          "segment/geometry/outline/r"
        ],
        "cross_ids": [],
        "validation": [],
        "hierarchical": [
          "segment/geometry/annulus",
          "segment/geometry/annulus/z"
        ],
        "units_compatible": [],
        "semantic_similarity": [],
        "documentation_refs": []
      },
      "coordinate1": null,
      "coordinate2": null,
      "timebase": null,
      "type": null
    },
    "iron_core/segment/geometry/annulus/z": {
      "path": "iron_core/segment/geometry/annulus/z",
      "documentation": "Centre height",
      "units": "m",
      "coordinates": [],
      "lifecycle": "active",
      "data_type": "FLT_0D",
      "introduced_after": null,
      "physics_context": null,
      "related_paths": [
        "segment/geometry/annulus/r",
        "segment/geometry/oblique/z",
        "segment/geometry/outline/r",
        "segment/geometry/annulus"
      ],
      "usage_examples": [],
      "validation_rules": {
        "min_value": null,
        "max_value": null,
        "units_required": true,
        "coordinate_check": null
      },
      "relationships": {
        "coordinates": [],
        "physics_related": [
          "segment/geometry/oblique/z",
          "segment/geometry/outline/r"
        ],
        "cross_ids": [],
        "validation": [],
        "hierarchical": [
          "segment/geometry/annulus",
          "segment/geometry/annulus/r"
        ],
        "units_compatible": [],
        "semantic_similarity": [],
        "documentation_refs": []
      },
      "coordinate1": null,
      "coordinate2": null,
      "timebase": null,
      "type": null
    },
    "iron_core/segment/geometry/annulus/radius_inner": {
      "path": "iron_core/segment/geometry/annulus/radius_inner",
      "documentation": "Inner radius",
      "units": "m",
      "coordinates": [],
      "lifecycle": "active",
      "data_type": "FLT_0D",
      "introduced_after": null,
      "physics_context": null,
      "related_paths": [
        "segment/geometry/annulus/r",
        "segment/geometry/annulus/z",
        "segment/geometry/oblique/z",
        "segment/geometry/outline/r",
        "segment/geometry/annulus"
      ],
      "usage_examples": [],
      "validation_rules": {
        "min_value": null,
        "max_value": null,
        "units_required": true,
        "coordinate_check": null
      },
      "relationships": {
        "coordinates": [],
        "physics_related": [
          "segment/geometry/oblique/z",
          "segment/geometry/outline/r"
        ],
        "cross_ids": [],
        "validation": [],
        "hierarchical": [
          "segment/geometry/annulus",
          "segment/geometry/annulus/r",
          "segment/geometry/annulus/z"
        ],
        "units_compatible": [],
        "semantic_similarity": [],
        "documentation_refs": []
      },
      "coordinate1": null,
      "coordinate2": null,
      "timebase": null,
      "type": null
    },
    "iron_core/segment/geometry/annulus/radius_outer": {
      "path": "iron_core/segment/geometry/annulus/radius_outer",
      "documentation": "Outer radius",
      "units": "m",
      "coordinates": [],
      "lifecycle": "active",
      "data_type": "FLT_0D",
      "introduced_after": null,
      "physics_context": null,
      "related_paths": [
        "segment/geometry/annulus/r",
        "segment/geometry/annulus/z",
        "segment/geometry/oblique/z",
        "segment/geometry/outline/r",
        "segment/geometry/annulus"
      ],
      "usage_examples": [],
      "validation_rules": {
        "min_value": null,
        "max_value": null,
        "units_required": true,
        "coordinate_check": null
      },
      "relationships": {
        "coordinates": [],
        "physics_related": [
          "segment/geometry/oblique/z",
          "segment/geometry/outline/r"
        ],
        "cross_ids": [],
        "validation": [],
        "hierarchical": [
          "segment/geometry/annulus",
          "segment/geometry/annulus/r",
          "segment/geometry/annulus/z"
        ],
        "units_compatible": [],
        "semantic_similarity": [],
        "documentation_refs": []
      },
      "coordinate1": null,
      "coordinate2": null,
      "timebase": null,
      "type": null
    },
    "iron_core/segment/geometry/thick_line": {
      "path": "iron_core/segment/geometry/thick_line",
      "documentation": "The element is approximated by a rectangle defined by a central segment and a thickness in the direction perpendicular to the segment",
      "units": "",
      "coordinates": [],
      "lifecycle": "active",
      "data_type": "structure",
      "introduced_after": null,
      "physics_context": null,
      "related_paths": [
        "segment/geometry/geometry_type",
        "segment/geometry/outline",
        "segment/geometry/rectangle",
        "segment/geometry/oblique",
        "segment/geometry/arcs_of_circle",
        "segment/geometry",
        "segment/geometry/thick_line/first_point",
        "segment/geometry/thick_line/second_point",
        "segment/geometry/thick_line/thickness",
        "segment/geometry/oblique/z"
      ],
      "usage_examples": [],
      "validation_rules": {
        "min_value": null,
        "max_value": null,
        "units_required": false,
        "coordinate_check": null
      },
      "relationships": {
        "coordinates": [],
        "physics_related": [
          "segment/geometry/oblique/z"
        ],
        "cross_ids": [],
        "validation": [],
        "hierarchical": [
          "segment/geometry",
          "segment/geometry/geometry_type",
          "segment/geometry/outline",
          "segment/geometry/rectangle",
          "segment/geometry/oblique",
          "segment/geometry/arcs_of_circle",
          "segment/geometry/thick_line/first_point",
          "segment/geometry/thick_line/second_point",
          "segment/geometry/thick_line/thickness"
        ],
        "units_compatible": [],
        "semantic_similarity": [],
        "documentation_refs": []
      },
      "coordinate1": null,
      "coordinate2": null,
      "timebase": null,
      "type": null,
      "structure_reference": "thick_line_static"
    },
    "iron_core/segment/geometry/thick_line/first_point": {
      "path": "iron_core/segment/geometry/thick_line/first_point",
      "documentation": "Position of the first point",
      "units": "",
      "coordinates": [],
      "lifecycle": "active",
      "data_type": "structure",
      "introduced_after": null,
      "physics_context": null,
      "related_paths": [
        "segment/geometry/thick_line/second_point",
        "segment/geometry/thick_line/thickness",
        "segment/geometry/oblique/z",
        "segment/geometry/thick_line",
        "segment/geometry/thick_line/first_point/r",
        "segment/geometry/thick_line/first_point/z"
      ],
      "usage_examples": [],
      "validation_rules": {
        "min_value": null,
        "max_value": null,
        "units_required": false,
        "coordinate_check": null
      },
      "relationships": {
        "coordinates": [],
        "physics_related": [
          "segment/geometry/oblique/z"
        ],
        "cross_ids": [],
        "validation": [],
        "hierarchical": [
          "segment/geometry/thick_line",
          "segment/geometry/thick_line/second_point",
          "segment/geometry/thick_line/thickness",
          "segment/geometry/thick_line/first_point/r",
          "segment/geometry/thick_line/first_point/z"
        ],
        "units_compatible": [],
        "semantic_similarity": [],
        "documentation_refs": []
      },
      "coordinate1": null,
      "coordinate2": null,
      "timebase": null,
      "type": null,
      "structure_reference": "rz0d_static"
    },
    "iron_core/segment/geometry/thick_line/first_point/r": {
      "path": "iron_core/segment/geometry/thick_line/first_point/r",
      "documentation": "Major radius",
      "units": "m",
      "coordinates": [],
      "lifecycle": "active",
      "data_type": "FLT_0D",
      "introduced_after": null,
      "physics_context": null,
      "related_paths": [
        "segment/geometry/thick_line/first_point/z",
        "segment/geometry/thick_line/first_point",
        "segment/geometry/oblique/z",
        "segment/geometry/outline/r"
      ],
      "usage_examples": [],
      "validation_rules": {
        "min_value": null,
        "max_value": null,
        "units_required": true,
        "coordinate_check": null
      },
      "relationships": {
        "coordinates": [],
        "physics_related": [
          "segment/geometry/oblique/z",
          "segment/geometry/outline/r"
        ],
        "cross_ids": [],
        "validation": [],
        "hierarchical": [
          "segment/geometry/thick_line/first_point",
          "segment/geometry/thick_line/first_point/z"
        ],
        "units_compatible": [],
        "semantic_similarity": [],
        "documentation_refs": []
      },
      "coordinate1": null,
      "coordinate2": null,
      "timebase": null,
      "type": null
    },
    "iron_core/segment/geometry/thick_line/first_point/z": {
      "path": "iron_core/segment/geometry/thick_line/first_point/z",
      "documentation": "Height",
      "units": "m",
      "coordinates": [],
      "lifecycle": "active",
      "data_type": "FLT_0D",
      "introduced_after": null,
      "physics_context": null,
      "related_paths": [
        "segment/geometry/thick_line/first_point/r",
        "segment/geometry/thick_line/first_point",
        "segment/geometry/oblique/z",
        "segment/geometry/outline/r"
      ],
      "usage_examples": [],
      "validation_rules": {
        "min_value": null,
        "max_value": null,
        "units_required": true,
        "coordinate_check": null
      },
      "relationships": {
        "coordinates": [],
        "physics_related": [
          "segment/geometry/oblique/z",
          "segment/geometry/outline/r"
        ],
        "cross_ids": [],
        "validation": [],
        "hierarchical": [
          "segment/geometry/thick_line/first_point",
          "segment/geometry/thick_line/first_point/r"
        ],
        "units_compatible": [],
        "semantic_similarity": [],
        "documentation_refs": []
      },
      "coordinate1": null,
      "coordinate2": null,
      "timebase": null,
      "type": null
    },
    "iron_core/segment/geometry/thick_line/second_point": {
      "path": "iron_core/segment/geometry/thick_line/second_point",
      "documentation": "Position of the second point",
      "units": "",
      "coordinates": [],
      "lifecycle": "active",
      "data_type": "structure",
      "introduced_after": null,
      "physics_context": null,
      "related_paths": [
        "segment/geometry/thick_line/first_point",
        "segment/geometry/thick_line/thickness",
        "segment/geometry/oblique/z",
        "segment/geometry/thick_line",
        "segment/geometry/thick_line/second_point/r",
        "segment/geometry/thick_line/second_point/z"
      ],
      "usage_examples": [],
      "validation_rules": {
        "min_value": null,
        "max_value": null,
        "units_required": false,
        "coordinate_check": null
      },
      "relationships": {
        "coordinates": [],
        "physics_related": [
          "segment/geometry/oblique/z"
        ],
        "cross_ids": [],
        "validation": [],
        "hierarchical": [
          "segment/geometry/thick_line",
          "segment/geometry/thick_line/first_point",
          "segment/geometry/thick_line/thickness",
          "segment/geometry/thick_line/second_point/r",
          "segment/geometry/thick_line/second_point/z"
        ],
        "units_compatible": [],
        "semantic_similarity": [],
        "documentation_refs": []
      },
      "coordinate1": null,
      "coordinate2": null,
      "timebase": null,
      "type": null,
      "structure_reference": "rz0d_static"
    },
    "iron_core/segment/geometry/thick_line/second_point/r": {
      "path": "iron_core/segment/geometry/thick_line/second_point/r",
      "documentation": "Major radius",
      "units": "m",
      "coordinates": [],
      "lifecycle": "active",
      "data_type": "FLT_0D",
      "introduced_after": null,
      "physics_context": null,
      "related_paths": [
        "segment/geometry/thick_line/second_point/z",
        "segment/geometry/thick_line/second_point",
        "segment/geometry/oblique/z",
        "segment/geometry/outline/r"
      ],
      "usage_examples": [],
      "validation_rules": {
        "min_value": null,
        "max_value": null,
        "units_required": true,
        "coordinate_check": null
      },
      "relationships": {
        "coordinates": [],
        "physics_related": [
          "segment/geometry/oblique/z",
          "segment/geometry/outline/r"
        ],
        "cross_ids": [],
        "validation": [],
        "hierarchical": [
          "segment/geometry/thick_line/second_point",
          "segment/geometry/thick_line/second_point/z"
        ],
        "units_compatible": [],
        "semantic_similarity": [],
        "documentation_refs": []
      },
      "coordinate1": null,
      "coordinate2": null,
      "timebase": null,
      "type": null
    },
    "iron_core/segment/geometry/thick_line/second_point/z": {
      "path": "iron_core/segment/geometry/thick_line/second_point/z",
      "documentation": "Height",
      "units": "m",
      "coordinates": [],
      "lifecycle": "active",
      "data_type": "FLT_0D",
      "introduced_after": null,
      "physics_context": null,
      "related_paths": [
        "segment/geometry/thick_line/second_point/r",
        "segment/geometry/thick_line/second_point",
        "segment/geometry/oblique/z",
        "segment/geometry/outline/r"
      ],
      "usage_examples": [],
      "validation_rules": {
        "min_value": null,
        "max_value": null,
        "units_required": true,
        "coordinate_check": null
      },
      "relationships": {
        "coordinates": [],
        "physics_related": [
          "segment/geometry/oblique/z",
          "segment/geometry/outline/r"
        ],
        "cross_ids": [],
        "validation": [],
        "hierarchical": [
          "segment/geometry/thick_line/second_point",
          "segment/geometry/thick_line/second_point/r"
        ],
        "units_compatible": [],
        "semantic_similarity": [],
        "documentation_refs": []
      },
      "coordinate1": null,
      "coordinate2": null,
      "timebase": null,
      "type": null
    },
    "iron_core/segment/geometry/thick_line/thickness": {
      "path": "iron_core/segment/geometry/thick_line/thickness",
      "documentation": "Thickness",
      "units": "m",
      "coordinates": [],
      "lifecycle": "active",
      "data_type": "FLT_0D",
      "introduced_after": null,
      "physics_context": null,
      "related_paths": [
        "segment/geometry/thick_line/first_point",
        "segment/geometry/thick_line/second_point",
        "segment/geometry/oblique/z",
        "segment/geometry/outline/r",
        "segment/geometry/thick_line"
      ],
      "usage_examples": [],
      "validation_rules": {
        "min_value": null,
        "max_value": null,
        "units_required": true,
        "coordinate_check": null
      },
      "relationships": {
        "coordinates": [],
        "physics_related": [
          "segment/geometry/oblique/z",
          "segment/geometry/outline/r"
        ],
        "cross_ids": [],
        "validation": [],
        "hierarchical": [
          "segment/geometry/thick_line",
          "segment/geometry/thick_line/first_point",
          "segment/geometry/thick_line/second_point"
        ],
        "units_compatible": [],
        "semantic_similarity": [],
        "documentation_refs": []
      },
      "coordinate1": null,
      "coordinate2": null,
      "timebase": null,
      "type": null
    },
    "iron_core/segment/magnetization_r": {
      "path": "iron_core/segment/magnetization_r",
      "documentation": "Magnetization M of the iron segment along the major radius axis, assumed to be constant inside a given iron segment. Reminder : H = 1/mu0 * B - mur * M;",
      "units": "T",
      "coordinates": [],
      "lifecycle": "active",
      "data_type": "structure",
      "introduced_after": null,
      "physics_context": null,
      "related_paths": [
        "segment/name",
        "segment/description",
        "segment/b_field",
        "segment",
        "segment/magnetization_r/data",
        "segment/magnetization_r/time",
        "segment/geometry/oblique/z"
      ],
      "usage_examples": [],
      "validation_rules": {
        "min_value": null,
        "max_value": null,
        "units_required": true,
        "coordinate_check": null
      },
      "relationships": {
        "coordinates": [],
        "physics_related": [
          "segment/geometry/oblique/z",
          "segment/b_field"
        ],
        "cross_ids": [],
        "validation": [],
        "hierarchical": [
          "segment",
          "segment/name",
          "segment/description",
          "segment/b_field",
          "segment/magnetization_r/data",
          "segment/magnetization_r/time"
        ],
        "units_compatible": [],
        "semantic_similarity": [],
        "documentation_refs": []
      },
      "coordinate1": null,
      "coordinate2": null,
      "timebase": null,
      "type": null,
      "structure_reference": "signal_flt_1d"
    },
    "iron_core/segment/magnetization_r/data": {
      "path": "iron_core/segment/magnetization_r/data",
      "documentation": "Data",
      "units": "T",
      "coordinates": [
        "segment(i1)/magnetization_r/time"
      ],
      "lifecycle": "active",
      "data_type": "FLT_1D",
      "introduced_after": null,
      "physics_context": null,
      "related_paths": [
        "segment/magnetization_r/time",
        "segment/magnetization_r",
        "segment/geometry/oblique/z",
        "segment/b_field"
      ],
      "usage_examples": [],
      "validation_rules": {
        "min_value": null,
        "max_value": null,
        "units_required": true,
        "coordinate_check": null
      },
      "relationships": {
        "coordinates": [],
        "physics_related": [
          "segment/geometry/oblique/z",
          "segment/b_field"
        ],
        "cross_ids": [],
        "validation": [],
        "hierarchical": [
          "segment/magnetization_r",
          "segment/magnetization_r/time"
        ],
        "units_compatible": [],
        "semantic_similarity": [],
        "documentation_refs": []
      },
      "coordinate1": null,
      "coordinate2": null,
      "timebase": null,
      "type": null,
      "temporal_context": "magnetization_r/time"
    },
    "iron_core/segment/magnetization_r/time": {
      "path": "iron_core/segment/magnetization_r/time",
      "documentation": "Time",
      "units": "s",
      "coordinates": [
        "1...N"
      ],
      "lifecycle": "active",
      "data_type": "FLT_1D",
      "introduced_after": null,
      "physics_context": null,
      "related_paths": [
        "segment/magnetization_r/data",
        "segment/magnetization_z/time",
        "segment/magnetization_r",
        "time",
        "segment/geometry/oblique/z"
      ],
      "usage_examples": [],
      "validation_rules": {
        "min_value": null,
        "max_value": null,
        "units_required": true,
        "coordinate_check": null
      },
      "relationships": {
        "coordinates": [],
        "physics_related": [
          "segment/geometry/oblique/z",
          "segment/magnetization_z/time",
          "time"
        ],
        "cross_ids": [],
        "validation": [],
        "hierarchical": [
          "segment/magnetization_r",
          "segment/magnetization_r/data"
        ],
        "units_compatible": [],
        "semantic_similarity": [],
        "documentation_refs": []
      },
      "coordinate1": null,
      "coordinate2": null,
      "timebase": null,
      "type": null,
      "temporal_context": "magnetization_r/time"
    },
    "iron_core/segment/magnetization_z": {
      "path": "iron_core/segment/magnetization_z",
      "documentation": "Magnetization M of the iron segment along the vertical axis, assumed to be constant inside a given iron segment. Reminder : H = 1/mu0 * B - mur * M;",
      "units": "T",
      "coordinates": [],
      "lifecycle": "active",
      "data_type": "structure",
      "introduced_after": null,
      "physics_context": null,
      "related_paths": [
        "segment/name",
        "segment/description",
        "segment/b_field",
        "segment",
        "segment/magnetization_z/data",
        "segment/magnetization_z/time",
        "segment/geometry/oblique/z"
      ],
      "usage_examples": [],
      "validation_rules": {
        "min_value": null,
        "max_value": null,
        "units_required": true,
        "coordinate_check": null
      },
      "relationships": {
        "coordinates": [],
        "physics_related": [
          "segment/geometry/oblique/z",
          "segment/b_field"
        ],
        "cross_ids": [],
        "validation": [],
        "hierarchical": [
          "segment",
          "segment/name",
          "segment/description",
          "segment/b_field",
          "segment/magnetization_z/data",
          "segment/magnetization_z/time"
        ],
        "units_compatible": [],
        "semantic_similarity": [],
        "documentation_refs": []
      },
      "coordinate1": null,
      "coordinate2": null,
      "timebase": null,
      "type": null,
      "structure_reference": "signal_flt_1d"
    },
    "iron_core/segment/magnetization_z/data": {
      "path": "iron_core/segment/magnetization_z/data",
      "documentation": "Data",
      "units": "T",
      "coordinates": [
        "segment(i1)/magnetization_z/time"
      ],
      "lifecycle": "active",
      "data_type": "FLT_1D",
      "introduced_after": null,
      "physics_context": null,
      "related_paths": [
        "segment/magnetization_z/time",
        "segment/magnetization_z",
        "segment/geometry/oblique/z",
        "segment/b_field"
      ],
      "usage_examples": [],
      "validation_rules": {
        "min_value": null,
        "max_value": null,
        "units_required": true,
        "coordinate_check": null
      },
      "relationships": {
        "coordinates": [],
        "physics_related": [
          "segment/geometry/oblique/z",
          "segment/b_field"
        ],
        "cross_ids": [],
        "validation": [],
        "hierarchical": [
          "segment/magnetization_z",
          "segment/magnetization_z/time"
        ],
        "units_compatible": [],
        "semantic_similarity": [],
        "documentation_refs": []
      },
      "coordinate1": null,
      "coordinate2": null,
      "timebase": null,
      "type": null,
      "temporal_context": "magnetization_z/time"
    },
    "iron_core/segment/magnetization_z/time": {
      "path": "iron_core/segment/magnetization_z/time",
      "documentation": "Time",
      "units": "s",
      "coordinates": [
        "1...N"
      ],
      "lifecycle": "active",
      "data_type": "FLT_1D",
      "introduced_after": null,
      "physics_context": null,
      "related_paths": [
        "segment/magnetization_z/data",
        "segment/magnetization_r/time",
        "segment/magnetization_z",
        "time",
        "segment/geometry/oblique/z"
      ],
      "usage_examples": [],
      "validation_rules": {
        "min_value": null,
        "max_value": null,
        "units_required": true,
        "coordinate_check": null
      },
      "relationships": {
        "coordinates": [],
        "physics_related": [
          "segment/geometry/oblique/z",
          "segment/magnetization_r/time",
          "time"
        ],
        "cross_ids": [],
        "validation": [],
        "hierarchical": [
          "segment/magnetization_z",
          "segment/magnetization_z/data"
        ],
        "units_compatible": [],
        "semantic_similarity": [],
        "documentation_refs": []
      },
      "coordinate1": null,
      "coordinate2": null,
      "timebase": null,
      "type": null,
      "temporal_context": "magnetization_z/time"
    },
    "iron_core/time": {
      "path": "iron_core/time",
      "documentation": "Generic time",
      "units": "s",
      "coordinates": [
        "1...N"
      ],
      "lifecycle": "active",
      "data_type": "FLT_1D",
      "introduced_after": null,
      "physics_context": null,
      "related_paths": [
        "segment/magnetization_r/time",
        "segment/magnetization_z/time"
      ],
      "usage_examples": [],
      "validation_rules": {
        "min_value": null,
        "max_value": null,
        "units_required": true,
        "coordinate_check": null
      },
      "relationships": {
        "coordinates": [],
        "physics_related": [
          "segment/magnetization_r/time",
          "segment/magnetization_z/time"
        ],
        "cross_ids": [],
        "validation": [],
        "hierarchical": [],
        "units_compatible": [],
        "semantic_similarity": [],
        "documentation_refs": []
      },
      "coordinate1": null,
      "coordinate2": null,
      "timebase": null,
      "type": null,
      "temporal_context": "time"
    }
  },
  "semantic_groups": {
    "structure_segment": [
      "iron_core/segment/name",
      "iron_core/segment/description",
      "iron_core/segment/geometry",
      "iron_core/segment/geometry/geometry_type",
      "iron_core/segment/geometry/outline",
      "iron_core/segment/geometry/rectangle",
      "iron_core/segment/geometry/oblique",
      "iron_core/segment/geometry/arcs_of_circle",
      "iron_core/segment/geometry/annulus",
      "iron_core/segment/geometry/thick_line",
      "iron_core/segment/geometry/thick_line/first_point",
      "iron_core/segment/geometry/thick_line/second_point"
    ],
    "units_T": [
      "iron_core/segment/b_field",
      "iron_core/segment/magnetization_r",
      "iron_core/segment/magnetization_r/data",
      "iron_core/segment/magnetization_z",
      "iron_core/segment/magnetization_z/data"
    ],
    "units_m": [
      "iron_core/segment/geometry/outline/r",
      "iron_core/segment/geometry/outline/z",
      "iron_core/segment/geometry/rectangle/r",
      "iron_core/segment/geometry/rectangle/z",
      "iron_core/segment/geometry/rectangle/width",
      "iron_core/segment/geometry/rectangle/height",
      "iron_core/segment/geometry/oblique/r",
      "iron_core/segment/geometry/oblique/z",
      "iron_core/segment/geometry/oblique/length_alpha",
      "iron_core/segment/geometry/oblique/length_beta",
      "iron_core/segment/geometry/arcs_of_circle/r",
      "iron_core/segment/geometry/arcs_of_circle/z",
      "iron_core/segment/geometry/arcs_of_circle/curvature_radii",
      "iron_core/segment/geometry/annulus/r",
      "iron_core/segment/geometry/annulus/z",
      "iron_core/segment/geometry/annulus/radius_inner",
      "iron_core/segment/geometry/annulus/radius_outer",
      "iron_core/segment/geometry/thick_line/first_point/r",
      "iron_core/segment/geometry/thick_line/first_point/z",
      "iron_core/segment/geometry/thick_line/second_point/r",
      "iron_core/segment/geometry/thick_line/second_point/z",
      "iron_core/segment/geometry/thick_line/thickness"
    ],
    "units_rad": [
      "iron_core/segment/geometry/oblique/alpha",
      "iron_core/segment/geometry/oblique/beta"
    ],
    "units_s": [
      "iron_core/segment/magnetization_r/time",
      "iron_core/segment/magnetization_z/time",
      "iron_core/time"
    ]
  }
}